francis/__init__.py
francis/__main__.py
francis_agent-1.0.10.dist-info/entry_points.txt
francis_agent-1.0.10.dist-info/licenses/LICENSE
francis_agent-1.0.10.dist-info/METADATA
francis_agent-1.0.10.dist-info/WHEEL
francis_agent-1.0.10.dist-info/RECORD
